.gitignore
CHANGES.rst
CONTRIBUTORS.rst
LICENSE.txt
README.rst
bootstrap.py
buildout.cfg
setup.py
djc/__init__.py
djc.recipe.egg-info/PKG-INFO
djc.recipe.egg-info/SOURCES.txt
djc.recipe.egg-info/dependency_links.txt
djc.recipe.egg-info/entry_points.txt
djc.recipe.egg-info/namespace_packages.txt
djc.recipe.egg-info/not-zip-safe
djc.recipe.egg-info/requires.txt
djc.recipe.egg-info/top_level.txt
djc/recipe/README.rst
djc/recipe/__init__.py
djc/recipe/copier.py
djc/recipe/copier.txt
djc/recipe/manage.py
djc/recipe/recipe.py
djc/recipe/settings.py.in
djc/recipe/utils.py
djc/recipe/wsgi.py
djc/recipe/testing/src/dummydjangoapp1/README.txt
djc/recipe/testing/src/dummydjangoapp1/setup.py
djc/recipe/testing/src/dummydjangoapp1/dummydjangoapp1/__init__.py
djc/recipe/testing/src/dummydjangoapp1/dummydjangoapp1/models.py.in
djc/recipe/testing/src/dummydjangoapp1/dummydjangoapp1/tests.py.in
djc/recipe/testing/src/dummydjangoapp1/dummydjangoapp1/views.py.in
djc/recipe/testing/src/dummydjangoapp1/dummydjangoapp1/static/lib1.js
djc/recipe/testing/src/dummydjangoapp1/dummydjangoapp1/static/main.css
djc/recipe/testing/src/dummydjangoapp2/README.txt
djc/recipe/testing/src/dummydjangoapp2/setup.py
djc/recipe/testing/src/dummydjangoapp2/dummydjangoapp2/__init__.py
djc/recipe/testing/src/dummydjangoapp2/dummydjangoapp2/models.py
djc/recipe/testing/src/dummydjangoapp2/dummydjangoapp2/tests.py
djc/recipe/testing/src/dummydjangoapp2/dummydjangoapp2/views.py
djc/recipe/testing/src/dummydjangoapp2/dummydjangoapp2/static/lib2.js
djc/recipe/testing/src/dummydjangoapp2/dummydjangoapp2/static/main.css
djc/recipe/testing/src/dummydjangoprj/README.txt
djc/recipe/testing/src/dummydjangoprj/setup.py
djc/recipe/testing/src/dummydjangoprj/dummydjangoprj/__init__.py
djc/recipe/testing/src/dummydjangoprj/dummydjangoprj/urls.py
djc/recipe/tests/__init__.py
djc/recipe/tests/test_copier.py
djc/recipe/tests/test_docs.py