Metadata-Version: 1.0
Name: djc.recipe
Version: 0.9.6
Summary: A Django buildout recipe
Home-page: http://github.com/abstract-open-solutions/djc.recipe
Author: Simone Deponti
Author-email: simone.deponti@abstract.it
License: BSD
Platform: UNKNOWN
Classifier: Framework :: Buildout
Classifier: Framework :: Django
Classifier: Intended Audience :: Developers
Classifier: Topic :: Software Development :: Build Tools
Classifier: License :: OSI Approved :: BSD License
